tiff/__init__.py
tiff/tiff.py
tiff/utils.py
tiff-0.1.0.dist-info/LICENSE
tiff-0.1.0.dist-info/WHEEL
tiff-0.1.0.dist-info/METADATA
tiff-0.1.0.dist-info/RECORD
