Metadata-Version: 2.1
Name: tiff
Version: 0.1.0
Summary: GeoTiff utils package
Author: Moleque
Author-email: molecada@yandex.ru
Requires-Python: >=3.6,<4.0
Classifier: Programming Language :: Python :: 3
Classifier: Programming Language :: Python :: 3.6
Classifier: Programming Language :: Python :: 3.7
Classifier: Programming Language :: Python :: 3.8
Classifier: Programming Language :: Python :: 3.9
Requires-Dist: geopy (>=2.1.0,<3.0.0)
Requires-Dist: numpy (>=1.19.5,<2.0.0)
Requires-Dist: pillow (>=8.2.0,<9.0.0)
Requires-Dist: pyproj (>=3.0.1,<4.0.0)
Requires-Dist: rasterio (>=1.2.3,<2.0.0)
